danpy/__init__.py
danpy/sb.py
danpy/test_sb.py
danpy/test_useful_functions.py
danpy/useful_functions.py
sb/__init__.py
sb/sb.py
sb/test_sb.py
danpy-1.5.1.dist-info/LICENSE.txt
danpy-1.5.1.dist-info/METADATA
danpy-1.5.1.dist-info/WHEEL
danpy-1.5.1.dist-info/top_level.txt
danpy-1.5.1.dist-info/RECORD
