Metadata-Version: 2.1
Name: danpy
Version: 1.5.1
Summary: Helpful functions for python.
Home-page: https://github.com/danhagen/danpy
Author: Daniel A Hagen
Author-email: dhagen@usc.edu
License: UNKNOWN
Platform: UNKNOWN
Classifier: Development Status :: 2 - Pre-Alpha
Classifier: Programming Language :: Python
Classifier: Programming Language :: Python :: 3
Classifier: Programming Language :: Python :: 3.6
Classifier: Programming Language :: Python :: 3.7
Requires-Dist: termcolor
Requires-Dist: scipy
Requires-Dist: numpy
Requires-Dist: matplotlib
